Workbook

Sheet Niveau initial
A1: Les formules de bases
C3: Somme | E3: Années
C4: € | E4: 0 | F4: =E4+1 -> 1 | G4: =F4+1 -> 2 | H4: =G4+1 -> 3 | I4: =H4+1 -> 4
A6: Investissement initial (Capex) | C6: =SUM(E6:I6) -> -10000 | E6: -10000
A7: Flux annuels (Recettes - Dépenses) | C7: =SUM(E7:I7) -> 16000 | F7: 4000 | G7: 4000 | H7: 4000 | I7: 4000
A9: Total | C9: =SUM(E9:I9) -> 6000 | E9: =SUM(E6:E7) -> -10000 | F9: =SUM(F6:F7) -> 4000 | G9: =SUM(G6:G7) -> 4000 | H9: =SUM(H6:H7) -> 4000 | I9: =SUM(I6:I7) -> 4000
A10: Total cumulatif | E10: =E9 -> -10000 | F10: =E10+F9 -> -6000 | G10: =F10+G9 -> -2000 | H10: =G10+H9 -> 2000 | I10: =H10+I9 -> 6000
A12: Temps de retour | C12: ans
A14: Taux d'actualisation | B14: 0.1
A16: Valeur actuelle nette
A17: - somme | C17: =SUM(E17:I17) -> 2679.4618 | E17: =E9/(1+$B$14)^E4 -> -10000 | F17: =F9/(1+$B$14)^F4 -> 3636.3636 | G17: =G9/(1+$B$14)^G4 -> 3305.7851 | H17: =H9/(1+$B$14)^H4 -> 3005.2592 | I17: =I9/(1+$B$14)^I4 -> 2732.0538
A18: - avec formule | C18: =E9+NPV(B14,F9:I9) -> 2679.4618
A20: TRI | C20: =IRR(E9:I9) -> 0.2186227
A24: Exemple de calcul d'un TRI simple :
C26: Années
C27: 0 | D27: =C27+1 -> 1 | E27: =D27+1 -> 2
B28: Capex | C28: 100
B29: Flux | D29: 65 | E29: 75
B30: Total | C30: =C29-C28 -> -100 | D30: =D29-D28 -> 65 | E30: =E29-E28 -> 75
B32: TRI : | C32: =IRR(C30:E30) -> 0.25
B34: VAN @ 25% : | D34: =D30/(1+$C$32) -> 52 | E34: =E30/(1+$C$32)^2 -> 48

Sheet Niveau intermédiare
A1: LCOE Solaire
A3: Dépenses
B4: Puissance | C4: Coût | F4: Somme | G4: VAN | I4: Années
B5: Wc | C5: €/Wc | D5: € | F5: € | G5: € | I5: 0 | J5: =I5+1 -> 1 | K5: =J5+1 -> 2 | L5: =K5+1 -> 3 | M5: =L5+1 -> 4 | N5: =M5+1 -> 5 | O5: =N5+1 -> 6 | P5: =O5+1 -> 7 | Q5: =P5+1 -> 8 | ... X5: =W5+1 -> 15
A6: Investissement | B6: 15000 | C6: 3 | D6: =B6*C6 -> 45000 | F6: =SUM(I6:X6) -> 45000 | G6: =I6+NPV($B$47,J6:X6) -> 45000 | I6: =D6 -> 45000
A7: Maintenance | B7: =B6 -> 15000 | C7: 0.02 | D7: =B7*C7 -> 300 | F7: =SUM(I7:X7) -> 4500 | G7: =I7+NPV($B$47,J7:X7) -> 2281.8239 | J7: =D7 -> 300 | K7: =J7 -> 300 | L7: =K7 -> 300 | M7: =L7 -> 300 | N7: =M7 -> 300 | O7: =N7 -> 300 | P7: =O7 -> 300 | Q7: =P7 -> 300 | R7: =Q7 -> 300 | ... X7: =W7 -> 300
A8: Total | F8: =SUM(F6:F7) -> 49500 | G8: =SUM(G6:G7) -> 47281.824
A10: Production
A12: Irradiation | B12: 5500 | C12: Wh/m²/jour
A13: Rendement | B13: 0.65
A14: Production par jour | B14: =B6*B12/1000*B13 -> 53625 | C14: Wh/jour
A15: Production par an | B15: =B14*365/1000 -> 19573.125 | C15: kWh/an | F15: =SUM(I15:X15) -> 313170 | G15: =I15+NPV($B$47,J15:X15) -> 168447.87 | I15: =$B$15 -> 19573.125 | J15: =$B$15 -> 19573.125 | K15: =$B$15 -> 19573.125 | L15: =$B$15 -> 19573.125 | M15: =$B$15 -> 19573.125 | N15: =$B$15 -> 19573.125 | O15: =$B$15 -> 19573.125 | P15: =$B$15 -> 19573.125 | ... X15: =$B$15 -> 19573.125
A17: Production PV = (Puissance PV x Irradiation) / (Rendement x 1000)
A19: LCOE
A21: LCOE simplifiée | B21: =F8/F15 -> 0.15806112 | C21: €/kWh
A23: Discount rate | B23: 0.1
A24: LCOE actualisée | B24: =G8/G15 -> 0.28069114 | C24: €/kWh
A26: LCOE = somme des dépenses / somme de la production * sur la durée de vie
A28: LCOE Groupe électrogène
A30: Dépenses
B31: Puissance | C31: Coût | F31: Somme | G31: VAN | I31: Années
B32: VA | C32: €/VA | D32: € | F32: € | G32: € | I32: 0 | J32: =I32+1 -> 1 | K32: =J32+1 -> 2 | L32: =K32+1 -> 3 | M32: =L32+1 -> 4 | N32: =M32+1 -> 5 | O32: =N32+1 -> 6 | P32: =O32+1 -> 7 | Q32: =P32+1 -> 8 | ... X32: =W32+1 -> 15
A33: Investissement | B33: 8000 | C33: 0.5 | D33: =B33*C33 -> 4000 | F33: =SUM(I33:X33) -> 16000 | G33: =I33+NPV($B$47,J33:X33) -> 13947.408 | I33: =D33 -> 4000 | N33: 4000 | S33: 4000 | X33: 4000
A34: Maintenance | B34: =B33 -> 8000 | C34: 0.09 | D34: =B34*C34 -> 720 | F34: =SUM(I34:X34) -> 10800 | G34: =I34+NPV($B$47,J34:X34) -> 5476.3772 | J34: =D34 -> 720 | K34: =J34 -> 720 | L34: =K34 -> 720 | M34: =L34 -> 720 | N34: =M34 -> 720 | O34: =N34 -> 720 | P34: =O34 -> 720 | Q34: =P34 -> 720 | R34: =Q34 -> 720 | ... X34: =W34 -> 720
B36: Conso | C36: Coût | F36: Somme | G36: VAN
B37: L/kWh | C37: €/L | D37: €/Wh | F37: € | G37: €
A38: Carburant | B38: 0.4 | C38: 1 | D38: =B38*C38 -> 0.4 | F38: =SUM(I38:X38) -> 125268 | G38: =I38+NPV($B$47,J38:X38) -> 67379.148 | I38: =$D$38*I15 -> 7829.25 | J38: =$D$38*J15 -> 7829.25 | K38: =$D$38*K15 -> 7829.25 | L38: =$D$38*L15 -> 7829.25 | M38: =$D$38*M15 -> 7829.25 | N38: =$D$38*N15 -> 7829.25 | O38: =$D$38*O15 -> 7829.25 | P38: =$D$38*P15 -> 7829.25 | ... X38: =$D$38*X15 -> 7829.25
A41: Total | F41: =SUM(F33:F34)+F38 -> 152068 | G41: =SUM(G33:G34)+G38 -> 86802.933
A43: LCOE
A45: LCOE simplifiée | B45: =F41/F15 -> 0.48557652 | C45: €/kWh
A47: Discount rate | B47: =B23 -> 0.1
A48: LCOE actualisée | B48: =G41/G15 -> 0.51531036 | C48: €/kWh
A50: LCOE = somme des dépenses / somme de la production * sur la durée de vie
A52: Temps de retour sur investissement
A55: Dépenses solaires | B55: =I4 -> Années
B56: 0 | C56: =B56+1 -> 1 | D56: =C56+1 -> 2 | E56: =D56+1 -> 3 | F56: =E56+1 -> 4 | G56: =F56+1 -> 5 | H56: =G56+1 -> 6 | I56: =H56+1 -> 7 | J56: =I56+1 -> 8 | ... Q56: =P56+1 -> 15
A57: Investissement | B57: =I6 -> 45000 | C57: =J6 -> 0 | D57: =K6 -> 0 | E57: =L6 -> 0 | F57: =M6 -> 0 | G57: =N6 -> 0 | H57: =O6 -> 0 | I57: =P6 -> 0 | ... Q57: =X6 -> 0
A58: Maintenance | B58: =I7 -> 0 | C58: =J7 -> 300 | D58: =K7 -> 300 | E58: =L7 -> 300 | F58: =M7 -> 300 | G58: =N7 -> 300 | H58: =O7 -> 300 | I58: =P7 -> 300 | ... Q58: =X7 -> 300
A60: Total "Solaire" | B60: =SUM(B57:B59) -> 45000 | C60: =SUM(C57:C59) -> 300 | D60: =SUM(D57:D59) -> 300 | E60: =SUM(E57:E59) -> 300 | F60: =SUM(F57:F59) -> 300 | G60: =SUM(G57:G59) -> 300 | H60: =SUM(H57:H59) -> 300 | I60: =SUM(I57:I59) -> 300 | ... Q60: =SUM(Q57:Q59) -> 300
A61: Total cumulé "Solaire" | B61: =B60 -> 45000 | C61: =B61+C60 -> 45300 | D61: =C61+D60 -> 45600 | E61: =D61+E60 -> 45900 | F61: =E61+F60 -> 46200 | G61: =F61+G60 -> 46500 | H61: =G61+H60 -> 46800 | I61: =H61+I60 -> 47100 | J61: =I61+J60 -> 47400 | ... Q61: =P61+Q60 -> 49500
A64: Dépenses groupe | B64: Années
B65: 0 | C65: =B65+1 -> 1 | D65: =C65+1 -> 2 | E65: =D65+1 -> 3 | F65: =E65+1 -> 4 | G65: =F65+1 -> 5 | H65: =G65+1 -> 6 | I65: =H65+1 -> 7 | J65: =I65+1 -> 8 | ... Q65: =P65+1 -> 15
A66: Investissement | B66: =I33 -> 4000 | C66: =J33 -> 0 | D66: =K33 -> 0 | E66: =L33 -> 0 | F66: =M33 -> 0 | G66: =N33 -> 4000 | H66: =O33 -> 0 | I66: =P33 -> 0 | ... Q66: =X33 -> 4000
A67: Maintenance | B67: =I34 -> 0 | C67: =J34 -> 720 | D67: =K34 -> 720 | E67: =L34 -> 720 | F67: =M34 -> 720 | G67: =N34 -> 720 | H67: =O34 -> 720 | I67: =P34 -> 720 | ... Q67: =X34 -> 720
A68: Carburant | B68: =I38 -> 7829.25 | C68: =J38 -> 7829.25 | D68: =K38 -> 7829.25 | E68: =L38 -> 7829.25 | F68: =M38 -> 7829.25 | G68: =N38 -> 7829.25 | H68: =O38 -> 7829.25 | I68: =P38 -> 7829.25 | ... Q68: =X38 -> 7829.25
A70: Total "Groupe" | B70: =SUM(B66:B69) -> 11829.25 | C70: =SUM(C66:C69) -> 8549.25 | D70: =SUM(D66:D69) -> 8549.25 | E70: =SUM(E66:E69) -> 8549.25 | F70: =SUM(F66:F69) -> 8549.25 | G70: =SUM(G66:G69) -> 12549.25 | H70: =SUM(H66:H69) -> 8549.25 | I70: =SUM(I66:I69) -> 8549.25 | ... Q70: =SUM(Q66:Q69) -> 12549.25
A71: Total cumulé "Groupe" | B71: =B70 -> 11829.25 | C71: =B71+C70 -> 20378.5 | D71: =C71+D70 -> 28927.75 | E71: =D71+E70 -> 37477 | F71: =E71+F70 -> 46026.25 | G71: =F71+G70 -> 58575.5 | H71: =G71+H70 -> 67124.75 | I71: =H71+I70 -> 75674 | J71: =I71+J70 -> 84223.25 | ... Q71: =P71+Q70 -> 152068
A74: Temps de retour sur investissement
A90: Taux de rentabilité interne
B92: Années
A93: Dépenses totales | B93: 0 | C93: =B93+1 -> 1 | D93: =C93+1 -> 2 | E93: =D93+1 -> 3 | F93: =E93+1 -> 4 | G93: =F93+1 -> 5 | H93: =G93+1 -> 6 | I93: =H93+1 -> 7 | J93: =I93+1 -> 8 | ... P93: =O93+1 -> 14
A94: Solaire | B94: =B60 -> 45000 | C94: =C60 -> 300 | D94: =D60 -> 300 | E94: =E60 -> 300 | F94: =F60 -> 300 | G94: =G60 -> 300 | H94: =H60 -> 300 | I94: =I60 -> 300 | ... P94: =P60 -> 300
A95: Groupe | B95: =B70 -> 11829.25 | C95: =C70 -> 8549.25 | D95: =D70 -> 8549.25 | E95: =E70 -> 8549.25 | F95: =F70 -> 8549.25 | G95: =G70 -> 12549.25 | H95: =H70 -> 8549.25 | I95: =I70 -> 8549.25 | ... P95: =P70 -> 8549.25
A96: Econiomies solaire | B96: =B95-B94 -> -33170.75 | C96: =C95-C94 -> 8249.25 | D96: =D95-D94 -> 8249.25 | E96: =E95-E94 -> 8249.25 | F96: =F95-F94 -> 8249.25 | G96: =G95-G94 -> 12249.25 | H96: =H95-H94 -> 8249.25 | I96: =I95-I94 -> 8249.25 | ... P96: =P95-P94 -> 8249.25
A98: TRI | B98: =IRR(B96:P96) -> 0.25097458

Sheet Niveau avancé
A1: Hypothèses économique
A3: Nombre d'années | B3: ans | C3: 15 | D3: non modifiable
A4: Taux d'actualisation | B4: % | C4: 0.1
A6: Solaire Qualité
B9: Unité | C9: Coût unitaire | D9: Quantité | E9: Coût total | G9: Remplacement | I9: VAN | J9: Années
B10: ¤ | C10: €/ ¤ | D10: # | E10: € | F10: % total | G10: ans | I10: # | J10: 0 | K10: =J10+1 -> 1 | L10: =K10+1 -> 2 | M10: =L10+1 -> 3 | N10: =M10+1 -> 4 | O10: =N10+1 -> 5 | P10: =O10+1 -> 6 | Q10: =P10+1 -> 7 | R10: =Q10+1 -> 8 | ... Y10: =X10+1 -> 15
A11: Investissement initial (Capex)
A13: Electronique de puissance | B13: kW | C13: 525 | D13: 5 | E13: =C13*D13 -> 2625 | F13: =E13/E$19 -> 0.16005122 | G13: 16 | I13: =NPV($C$4,K13:Y13)+J13 -> 2625 | J13: =E13 -> 2625 | K13: =IF(ROUND(K$10/$G13,0)=K$10/$G13,1,0)*$J13 -> 0 | L13: =IF(ROUND(L$10/$G13,0)=L$10/$G13,1,0)*$J13 -> 0 | M13: =IF(ROUND(M$10/$G13,0)=M$10/$G13,1,0)*$J13 -> 0 | N13: =IF(ROUND(N$10/$G13,0)=N$10/$G13,1,0)*$J13 -> 0 | O13: =IF(ROUND(O$10/$G13,0)=O$10/$G13,1,0)*$J13 -> 0 | P13: =IF(ROUND(P$10/$G13,0)=P$10/$G13,1,0)*$J13 -> 0 | Q13: =IF(ROUND(Q$10/$G13,0)=Q$10/$G13,1,0)*$J13 -> 0 | R13: =IF(ROUND(R$10/$G13,0)=R$10/$G13,1,0)*$J13 -> 0 | ... Y13: =IF(ROUND(Y$10/$G13,0)=Y$10/$G13,1,0)*$J13 -> 0
A14: Batteries | B14: kWh | C14: 425 | D14: 10 | E14: =C14*D14 -> 4250 | F14: =E14/E$19 -> 0.25913054 | G14: 16 | I14: =NPV($C$4,K14:Y14)+J14 -> 4250 | J14: =E14 -> 4250 | K14: =IF(ROUND(K$10/$G14,0)=K$10/$G14,1,0)*$J14 -> 0 | L14: =IF(ROUND(L$10/$G14,0)=L$10/$G14,1,0)*$J14 -> 0 | M14: =IF(ROUND(M$10/$G14,0)=M$10/$G14,1,0)*$J14 -> 0 | N14: =IF(ROUND(N$10/$G14,0)=N$10/$G14,1,0)*$J14 -> 0 | O14: =IF(ROUND(O$10/$G14,0)=O$10/$G14,1,0)*$J14 -> 0 | P14: =IF(ROUND(P$10/$G14,0)=P$10/$G14,1,0)*$J14 -> 0 | Q14: =IF(ROUND(Q$10/$G14,0)=Q$10/$G14,1,0)*$J14 -> 0 | R14: =IF(ROUND(R$10/$G14,0)=R$10/$G14,1,0)*$J14 -> 0 | ... Y14: =IF(ROUND(Y$10/$G14,0)=Y$10/$G14,1,0)*$J14 -> 0
A15: Panneaux | B15: Wc | C15: 0.4 | D15: 5500 | E15: =C15*D15 -> 2200 | F15: =E15/E$19 -> 0.13413816 | G15: 25 | I15: =NPV($C$4,K15:Y15)+J15 -> 2200 | J15: =E15 -> 2200 | K15: =IF(ROUND(K$10/$G15,0)=K$10/$G15,1,0)*$J15 -> 0 | L15: =IF(ROUND(L$10/$G15,0)=L$10/$G15,1,0)*$J15 -> 0 | M15: =IF(ROUND(M$10/$G15,0)=M$10/$G15,1,0)*$J15 -> 0 | N15: =IF(ROUND(N$10/$G15,0)=N$10/$G15,1,0)*$J15 -> 0 | O15: =IF(ROUND(O$10/$G15,0)=O$10/$G15,1,0)*$J15 -> 0 | P15: =IF(ROUND(P$10/$G15,0)=P$10/$G15,1,0)*$J15 -> 0 | Q15: =IF(ROUND(Q$10/$G15,0)=Q$10/$G15,1,0)*$J15 -> 0 | R15: =IF(ROUND(R$10/$G15,0)=R$10/$G15,1,0)*$J15 -> 0 | ... Y15: =IF(ROUND(Y$10/$G15,0)=Y$10/$G15,1,0)*$J15 -> 0
A16: Câbles et accessoires | B16: Wc | C16: 0.2 | D16: =$D$15 -> 5500 | E16: =C16*D16 -> 1100 | F16: =E16/E$19 -> 0.067069081 | G16: 25 | I16: =NPV($C$4,K16:Y16)+J16 -> 1100 | J16: =E16 -> 1100 | K16: =IF(ROUND(K$10/$G16,0)=K$10/$G16,1,0)*$J16 -> 0 | L16: =IF(ROUND(L$10/$G16,0)=L$10/$G16,1,0)*$J16 -> 0 | M16: =IF(ROUND(M$10/$G16,0)=M$10/$G16,1,0)*$J16 -> 0 | N16: =IF(ROUND(N$10/$G16,0)=N$10/$G16,1,0)*$J16 -> 0 | O16: =IF(ROUND(O$10/$G16,0)=O$10/$G16,1,0)*$J16 -> 0 | P16: =IF(ROUND(P$10/$G16,0)=P$10/$G16,1,0)*$J16 -> 0 | Q16: =IF(ROUND(Q$10/$G16,0)=Q$10/$G16,1,0)*$J16 -> 0 | R16: =IF(ROUND(R$10/$G16,0)=R$10/$G16,1,0)*$J16 -> 0 | ... Y16: =IF(ROUND(Y$10/$G16,0)=Y$10/$G16,1,0)*$J16 -> 0
A17: Installation | B17: Wc | C17: 0.25 | D17: =$D$15 -> 5500 | E17: =C17*D17 -> 1375 | F17: =E17/E$19 -> 0.083836351 | I17: =NPV($C$4,K17:Y17)+J17 -> 1375 | J17: =E17 -> 1375 | K17: =SUM(K13:K16)*$F17 -> 0 | L17: =SUM(L13:L16)*$F17 -> 0 | M17: =SUM(M13:M16)*$F17 -> 0 | N17: =SUM(N13:N16)*$F17 -> 0 | O17: =SUM(O13:O16)*$F17 -> 0 | P17: =SUM(P13:P16)*$F17 -> 0 | Q17: =SUM(Q13:Q16)*$F17 -> 0 | R17: =SUM(R13:R16)*$F17 -> 0 | ... Y17: =SUM(Y13:Y16)*$F17 -> 0
A18: Markup | B18: Wc | C18: =E18/D18 -> 0.882 | D18: =$D$15 -> 5500 | E18: =SUM(E$13:E17)*F18 -> 4851 | F18: 0.42 | I18: =NPV($C$4,K18:Y18)+J18 -> 4851 | J18: =E18 -> 4851 | K18: =SUM(K13:K17)*$F18 -> 0 | L18: =SUM(L13:L17)*$F18 -> 0 | M18: =SUM(M13:M17)*$F18 -> 0 | N18: =SUM(N13:N17)*$F18 -> 0 | O18: =SUM(O13:O17)*$F18 -> 0 | P18: =SUM(P13:P17)*$F18 -> 0 | Q18: =SUM(Q13:Q17)*$F18 -> 0 | R18: =SUM(R13:R17)*$F18 -> 0 | ... Y18: =SUM(Y13:Y17)*$F18 -> 0
A19: Total | B19: Wc | C19: =E19/D19 -> 2.982 | D19: =$D$15 -> 5500 | E19: =SUM(E13:E18) -> 16401 | F19: =E19/SUM(E$13:E18) -> 1 | I19: =NPV($C$4,K19:Y19)+J19 -> 16401 | J19: =SUM(J13:J18) -> 16401 | K19: =SUM(K13:K18)*$F19 -> 0 | L19: =SUM(L13:L18)*$F19 -> 0 | M19: =SUM(M13:M18)*$F19 -> 0 | N19: =SUM(N13:N18)*$F19 -> 0 | O19: =SUM(O13:O18)*$F19 -> 0 | P19: =SUM(P13:P18)*$F19 -> 0 | Q19: =SUM(Q13:Q18)*$F19 -> 0 | R19: =SUM(R13:R18)*$F19 -> 0 | ... Y19: =SUM(Y13:Y18)*$F19 -> 0
A21: Marge | C21: =E18/E19 -> 0.29577465
A23: Maintenance (Opex) | B23: Wc | C23: 0.02 | D23: =D15 -> 5500 | E23: =C23*D23 -> 110 | F23: =E23/E19 -> 0.0067069081 | G23: 1 | I23: =NPV($C$4,K23:Y23)+K23 -> 946.66875 | K23: =E23 -> 110 | L23: =$K$23 -> 110 | M23: =$K$23 -> 110 | N23: =$K$23 -> 110 | O23: =$K$23 -> 110 | P23: =$K$23 -> 110 | Q23: =$K$23 -> 110 | R23: =$K$23 -> 110 | S23: =$K$23 -> 110 | ... Y23: =$K$23 -> 110
A25: Capex + Opex | B25: Wc | C25: =E25/D25 -> 3.1341216 | D25: =$D$15 -> 5500 | E25: =I25 -> 17237.669 | F25: =E25/E19 -> 1.0510133 | I25: =NPV($C$4,K25:Y25)+J25 -> 17237.669 | J25: =J23+J19 -> 16401 | K25: =K23+K19 -> 110 | L25: =L23+L19 -> 110 | M25: =M23+M19 -> 110 | N25: =N23+N19 -> 110 | O25: =O23+O19 -> 110 | P25: =P23+P19 -> 110 | Q25: =Q23+Q19 -> 110 | ... Y25: =Y23+Y19 -> 110
A27: Production
A29: Irradiation | B29: kWh/m²/j | C29: 5.5
A31: Rendement initial
A32: Panneaux | B32: % | C32: 0.9
A33: Régulateur | B33: % | C33: 0.95
A34: Câbles | B34: % | C34: 0.95
A35: Batteries | B35: % | C35: 0.95
A36: Convertisseur | B36: % | C36: 0.92
A37: Total | C37: =C32*C33*C34*C35*C36 -> 0.7099065
A39: Perte de rendement total | B39: Pts | C39: 8
A40: Perte de rendement par an | B40: Pts | C40: =C39/$C$3 -> 0.53333333 | I40: VAN | J40: Années
A41: Rendement dernière année | B41: % | C41: =(C37*100-C39)/100 -> 0.6299065 | I41: # | J41: 0 | K41: =J41+1 -> 1 | L41: =K41+1 -> 2 | M41: =L41+1 -> 3 | N41: =M41+1 -> 4 | O41: =N41+1 -> 5 | P41: =O41+1 -> 6 | Q41: =P41+1 -> 7 | R41: =Q41+1 -> 8 | ... Y41: =X41+1 -> 15
A43: Rendement du système | B43: % | K43: ='Niveau avancé'!C37 -> 0.7099065 | L43: =(K43*100-'Niveau avancé'!$C$40)/100 -> 0.70457317 | M43: =(L43*100-'Niveau avancé'!$C$40)/100 -> 0.69923983 | N43: =(M43*100-'Niveau avancé'!$C$40)/100 -> 0.6939065 | O43: =(N43*100-'Niveau avancé'!$C$40)/100 -> 0.68857317 | P43: =(O43*100-'Niveau avancé'!$C$40)/100 -> 0.68323983 | Q43: =(P43*100-'Niveau avancé'!$C$40)/100 -> 0.6779065 | R43: =(Q43*100-'Niveau avancé'!$C$40)/100 -> 0.67257317 | S43: =(R43*100-'Niveau avancé'!$C$40)/100 -> 0.66723983 | ... Y43: =(X43*100-'Niveau avancé'!$C$40)/100 -> 0.63523983
A44: Production annuelle | B44: kWh | I44: =NPV($C$4,K44:Y44)+J44 -> 57253.975 | K44: =$D$15*K43*'Niveau avancé'!$C$29*365/1000 -> 7838.2551 | L44: =$D$15*L43*'Niveau avancé'!$C$29*365/1000 -> 7779.3685 | M44: =$D$15*M43*'Niveau avancé'!$C$29*365/1000 -> 7720.4818 | N44: =$D$15*N43*'Niveau avancé'!$C$29*365/1000 -> 7661.5951 | O44: =$D$15*O43*'Niveau avancé'!$C$29*365/1000 -> 7602.7085 | P44: =$D$15*P43*'Niveau avancé'!$C$29*365/1000 -> 7543.8218 | Q44: =$D$15*Q43*'Niveau avancé'!$C$29*365/1000 -> 7484.9351 | R44: =$D$15*R43*'Niveau avancé'!$C$29*365/1000 -> 7426.0485 | ... Y44: =$D$15*Y43*'Niveau avancé'!$C$29*365/1000 -> 7013.8418
A46: LCOE | B46: €/kWh | C46: =(I19+I23)/I44 -> 0.30299501
A48: Solaire Low Cost
B51: Unité | C51: Coût unitaire | D51: Quantité | E51: Coût total | G51: Remplacement | I51: VAN | J51: Années
B52: ¤ | C52: €/ ¤ | D52: # | E52: € | F52: % tot sup | G52: ans | I52: # | J52: 0 | K52: =J52+1 -> 1 | L52: =K52+1 -> 2 | M52: =L52+1 -> 3 | N52: =M52+1 -> 4 | O52: =N52+1 -> 5 | P52: =O52+1 -> 6 | Q52: =P52+1 -> 7 | R52: =Q52+1 -> 8 | ... Y52: =X52+1 -> 15
A53: Investissement initial (Capex)
A55: Electronique de puissance | B55: kW | C55: 250 | D55: 5 | E55: =C55*D55 -> 1250 | F55: =E55/E$61 -> 0.11936023 | G55: 5 | I55: =NPV($C$4,K55:X55)+J55 -> 2508.0808 | J55: =E55 -> 1250 | K55: =IF(ROUND(K$52/$G55,0)=K$52/$G55,1,0)*$J55 -> 0 | L55: =IF(ROUND(L$52/$G55,0)=L$52/$G55,1,0)*$J55 -> 0 | M55: =IF(ROUND(M$52/$G55,0)=M$52/$G55,1,0)*$J55 -> 0 | N55: =IF(ROUND(N$52/$G55,0)=N$52/$G55,1,0)*$J55 -> 0 | O55: =IF(ROUND(O$52/$G55,0)=O$52/$G55,1,0)*$J55 -> 1250 | P55: =IF(ROUND(P$52/$G55,0)=P$52/$G55,1,0)*$J55 -> 0 | Q55: =IF(ROUND(Q$52/$G55,0)=Q$52/$G55,1,0)*$J55 -> 0 | R55: =IF(ROUND(R$52/$G55,0)=R$52/$G55,1,0)*$J55 -> 0 | ... Y55: =IF(ROUND(Y$52/$G55,0)=Y$52/$G55,1,0)*$J55 -> 1250
A56: Batteries | B56: kWh | C56: 125 | D56: 16 | E56: =C56*D56 -> 2000 | F56: =E56/E$61 -> 0.19097637 | G56: 4 | I56: =NPV($C$4,K56:X56)+J56 -> 4936.3033 | J56: =E56 -> 2000 | K56: =IF(ROUND(K$52/$G56,0)=K$52/$G56,1,0)*$J56 -> 0 | L56: =IF(ROUND(L$52/$G56,0)=L$52/$G56,1,0)*$J56 -> 0 | M56: =IF(ROUND(M$52/$G56,0)=M$52/$G56,1,0)*$J56 -> 0 | N56: =IF(ROUND(N$52/$G56,0)=N$52/$G56,1,0)*$J56 -> 2000 | O56: =IF(ROUND(O$52/$G56,0)=O$52/$G56,1,0)*$J56 -> 0 | P56: =IF(ROUND(P$52/$G56,0)=P$52/$G56,1,0)*$J56 -> 0 | Q56: =IF(ROUND(Q$52/$G56,0)=Q$52/$G56,1,0)*$J56 -> 0 | R56: =IF(ROUND(R$52/$G56,0)=R$52/$G56,1,0)*$J56 -> 2000 | ... Y56: =IF(ROUND(Y$52/$G56,0)=Y$52/$G56,1,0)*$J56 -> 0
A57: Panneaux | B57: Wc | C57: 0.3 | D57: 5500 | E57: =C57*D57 -> 1650 | F57: =E57/E$61 -> 0.1575555 | G57: 25 | I57: =NPV($C$4,K57:X57)+J57 -> 1650 | J57: =E57 -> 1650 | K57: =IF(ROUND(K$52/$G57,0)=K$52/$G57,1,0)*$J57 -> 0 | L57: =IF(ROUND(L$52/$G57,0)=L$52/$G57,1,0)*$J57 -> 0 | M57: =IF(ROUND(M$52/$G57,0)=M$52/$G57,1,0)*$J57 -> 0 | N57: =IF(ROUND(N$52/$G57,0)=N$52/$G57,1,0)*$J57 -> 0 | O57: =IF(ROUND(O$52/$G57,0)=O$52/$G57,1,0)*$J57 -> 0 | P57: =IF(ROUND(P$52/$G57,0)=P$52/$G57,1,0)*$J57 -> 0 | Q57: =IF(ROUND(Q$52/$G57,0)=Q$52/$G57,1,0)*$J57 -> 0 | R57: =IF(ROUND(R$52/$G57,0)=R$52/$G57,1,0)*$J57 -> 0 | ... Y57: =IF(ROUND(Y$52/$G57,0)=Y$52/$G57,1,0)*$J57 -> 0
A58: Câbles et accessoires | B58: Wc | C58: 0.2 | D58: =$D$15 -> 5500 | E58: =C58*D58 -> 1100 | F58: =E58/E$61 -> 0.105037 | G58: 25 | I58: =NPV($C$4,K58:X58)+J58 -> 1100 | J58: =E58 -> 1100 | K58: =IF(ROUND(K$52/$G58,0)=K$52/$G58,1,0)*$J58 -> 0 | L58: =IF(ROUND(L$52/$G58,0)=L$52/$G58,1,0)*$J58 -> 0 | M58: =IF(ROUND(M$52/$G58,0)=M$52/$G58,1,0)*$J58 -> 0 | N58: =IF(ROUND(N$52/$G58,0)=N$52/$G58,1,0)*$J58 -> 0 | O58: =IF(ROUND(O$52/$G58,0)=O$52/$G58,1,0)*$J58 -> 0 | P58: =IF(ROUND(P$52/$G58,0)=P$52/$G58,1,0)*$J58 -> 0 | Q58: =IF(ROUND(Q$52/$G58,0)=Q$52/$G58,1,0)*$J58 -> 0 | R58: =IF(ROUND(R$52/$G58,0)=R$52/$G58,1,0)*$J58 -> 0 | ... Y58: =IF(ROUND(Y$52/$G58,0)=Y$52/$G58,1,0)*$J58 -> 0
A59: Installation | B59: Wc | C59: 0.25 | D59: =$D$15 -> 5500 | E59: =C59*D59 -> 1375 | F59: =E59/E$61 -> 0.13129625 | I59: =NPV($C$4,K59:X59)+J59 -> 1925.7069 | J59: =E59 -> 1375 | K59: =SUM(K55:K58)*$F59 -> 0 | L59: =SUM(L55:L58)*$F59 -> 0 | M59: =SUM(M55:M58)*$F59 -> 0 | N59: =SUM(N55:N58)*$F59 -> 262.5925 | O59: =SUM(O55:O58)*$F59 -> 164.12032 | P59: =SUM(P55:P58)*$F59 -> 0 | Q59: =SUM(Q55:Q58)*$F59 -> 0 | R59: =SUM(R55:R58)*$F59 -> 262.5925 | ... Y59: =SUM(Y55:Y58)*$F59 -> 164.12032
A60: Marge | B60: Wc | C60: =E60/D60 -> 0.56318182 | D60: =$D$15 -> 5500 | E60: =SUM(E$55:E59)*F60 -> 3097.5 | F60: 0.42 | I60: =NPV($C$4,K60:X60)+J60 -> 5090.4382 | J60: =E60 -> 3097.5 | K60: =SUM(K55:K59)*$F60 -> 0 | L60: =SUM(L55:L59)*$F60 -> 0 | M60: =SUM(M55:M59)*$F60 -> 0 | N60: =SUM(N55:N59)*$F60 -> 950.28885 | O60: =SUM(O55:O59)*$F60 -> 593.93053 | P60: =SUM(P55:P59)*$F60 -> 0 | Q60: =SUM(Q55:Q59)*$F60 -> 0 | R60: =SUM(R55:R59)*$F60 -> 950.28885 | ... Y60: =SUM(Y55:Y59)*$F60 -> 593.93053
A61: Total | B61: Wc | C61: =E61/D61 -> 1.9040909 | D61: =$D$15 -> 5500 | E61: =SUM(E55:E60) -> 10472.5 | F61: =E61/SUM(E$13:E60) -> 0.17275034 | I61: =NPV($C$4,K61:X61)+J61 -> 17210.529 | J61: =SUM(J55:J60) -> 10472.5 | K61: =SUM(K55:K60) -> 0 | L61: =SUM(L55:L60) -> 0 | M61: =SUM(M55:M60) -> 0 | N61: =SUM(N55:N60) -> 3212.8814 | O61: =SUM(O55:O60) -> 2008.0508 | P61: =SUM(P55:P60) -> 0 | Q61: =SUM(Q55:Q60) -> 0 | ... Y61: =SUM(Y55:Y60) -> 2008.0508
A63: Marge | C63: =E60/E61 -> 0.29577465
A65: Maintenance (Opex) | B65: Wc | C65: 0.03 | D65: =D57 -> 5500 | E65: =C65*D65 -> 165 | F65: =E65/E61 -> 0.01575555 | G65: 1 | I65: =NPV($C$4,K65:X65)+J65 -> 1215.5034 | K65: =$E$65 -> 165 | L65: =$E$65 -> 165 | M65: =$E$65 -> 165 | N65: =$E$65 -> 165 | O65: =$E$65 -> 165 | P65: =$E$65 -> 165 | Q65: =$E$65 -> 165 | R65: =$E$65 -> 165 | ... Y65: =$E$65 -> 165
A67: Capex + Opex | B67: Wc | C67: =E67/D67 -> 3.3501877 | D67: =$D$15 -> 5500 | E67: =I67 -> 18426.033 | F67: =E67/E61 -> 1.7594684 | I67: =I65+I61 -> 18426.033 | J67: =J65+J61 -> 10472.5 | K67: =K65+K61 -> 165 | L67: =L65+L61 -> 165 | M67: =M65+M61 -> 165 | N67: =N65+N61 -> 3377.8814 | O67: =O65+O61 -> 2173.0508 | P67: =P65+P61 -> 165 | ... Y67: =Y65+Y61 -> 2173.0508
A69: Production
A71: Irradiation | B71: kWh/m²/j | C71: 5.5
A73: Rendement initial
A74: Panneaux | B74: % | C74: 0.85
A75: Régulateur | B75: % | C75: 0.9
A76: Câbles | B76: % | C76: 0.95
A77: Batteries | B77: % | C77: 0.8
A78: Convertisseur | B78: % | C78: 0.85
A79: Total | C79: =C74*C75*C76*C77*C78 -> 0.49419
A81: Perte de rendement total | B81: Pts | C81: 10
A82: Perte de rendement par an | B82: Pts | C82: =C81/$C$3 -> 0.66666667
A83: Rendement dernière année | B83: % | C83: =(C79*100-C81)/100 -> 0.39419 | I83: VAN | J83: Années
I84: # | J84: 0 | K84: =J84+1 -> 1 | L84: =K84+1 -> 2 | M84: =L84+1 -> 3 | N84: =M84+1 -> 4 | O84: =N84+1 -> 5 | P84: =O84+1 -> 6 | Q84: =P84+1 -> 7 | R84: =Q84+1 -> 8 | ... Y84: =X84+1 -> 15
A85: Rendement du système | B85: % | K85: ='Niveau avancé'!C79 -> 0.49419 | L85: =(K85*100-'Niveau avancé'!$C$40)/100 -> 0.48885667 | M85: =(L85*100-'Niveau avancé'!$C$40)/100 -> 0.48352333 | N85: =(M85*100-'Niveau avancé'!$C$40)/100 -> 0.47819 | O85: =(N85*100-'Niveau avancé'!$C$40)/100 -> 0.47285667 | P85: =(O85*100-'Niveau avancé'!$C$40)/100 -> 0.46752333 | Q85: =(P85*100-'Niveau avancé'!$C$40)/100 -> 0.46219 | R85: =(Q85*100-'Niveau avancé'!$C$40)/100 -> 0.45685667 | S85: =(R85*100-'Niveau avancé'!$C$40)/100 -> 0.45152333 | ... Y85: =(X85*100-'Niveau avancé'!$C$40)/100 -> 0.41952333
A86: Production annuelle | B86: kWh | I86: =NPV($C$4,K86:X86)+J86 -> 38029.09 | K86: =$D$15*K85*'Niveau avancé'!$C$29*365/1000 -> 5456.4753 | L86: =$D$15*L85*'Niveau avancé'!$C$29*365/1000 -> 5397.5887 | M86: =$D$15*M85*'Niveau avancé'!$C$29*365/1000 -> 5338.702 | N86: =$D$15*N85*'Niveau avancé'!$C$29*365/1000 -> 5279.8153 | O86: =$D$15*O85*'Niveau avancé'!$C$29*365/1000 -> 5220.9287 | P86: =$D$15*P85*'Niveau avancé'!$C$29*365/1000 -> 5162.042 | Q86: =$D$15*Q85*'Niveau avancé'!$C$29*365/1000 -> 5103.1553 | R86: =$D$15*R85*'Niveau avancé'!$C$29*365/1000 -> 5044.2687 | ... Y86: =$D$15*Y85*'Niveau avancé'!$C$29*365/1000 -> 4632.062
A88: LCOE | B88: €/kWh | C88: =(I61+I65)/I86 -> 0.48452468
A89: Différence avec "Qualité" | C89: =D111 -> 0.60787378
A91: Comparatif
C93: Total
C94: non actualisé | D94: actualisé | J94: Années
A95: Dépenses totales (Capex + Opex) | J95: 0 | K95: =J95+1 -> 1 | L95: =K95+1 -> 2 | M95: =L95+1 -> 3 | N95: =M95+1 -> 4 | O95: =N95+1 -> 5 | P95: =O95+1 -> 6 | Q95: =P95+1 -> 7 | R95: =Q95+1 -> 8 | ... Y95: =X95+1 -> 15
A96: "Qualité" | B96: € | C96: =SUM(J96:Y96) -> 18051 | D96: =NPV($C$4,J96:Y96) -> 15670.608 | J96: =J23+J19 -> 16401 | K96: =K23+K19 -> 110 | L96: =L23+L19 -> 110 | M96: =M23+M19 -> 110 | N96: =N23+N19 -> 110 | O96: =O23+O19 -> 110 | P96: =P23+P19 -> 110 | Q96: =Q23+Q19 -> 110 | ... Y96: =Y23+Y19 -> 110
A97: "Low cost" | B97: € | C97: =SUM(J97:Y97) -> 28610.297 | D97: =NPV($C$4,J97:Y97) -> 17223.858 | J97: =J65+J61 -> 10472.5 | K97: =K65+K61 -> 165 | L97: =L65+L61 -> 165 | M97: =M65+M61 -> 165 | N97: =N65+N61 -> 3377.8814 | O97: =O65+O61 -> 2173.0508 | P97: =P65+P61 -> 165 | Q97: =Q65+Q61 -> 165 | ... Y97: =Y65+Y61 -> 2173.0508
A98: Econiomies Qualité | B98: € | C98: =SUM(J98:Y98) -> 10559.297 | D98: =NPV($C$4,J98:Y98) -> 1553.25 | J98: =J97-J96 -> -5928.5 | K98: =K97-K96 -> 55 | L98: =L97-L96 -> 55 | M98: =M97-M96 -> 55 | N98: =N97-N96 -> 3267.8814 | O98: =O97-O96 -> 2063.0508 | P98: =P97-P96 -> 55 | Q98: =Q97-Q96 -> 55 | ... Y98: =Y97-Y96 -> 2063.0508
B99: % | C99: =C98/C96 -> 0.58497017 | D99: =D98/D96 -> 0.09911868
A101: Production annnuelle
A102: "Qualité" | B102: kWh | C102: =SUM(J102:Y102) -> 111390.73 | D102: =NPV($C$4,J102:Y102) -> 52049.068 | J102: =J44 -> 0 | K102: =K44 -> 7838.2551 | L102: =L44 -> 7779.3685 | M102: =M44 -> 7720.4818 | N102: =N44 -> 7661.5951 | O102: =O44 -> 7602.7085 | P102: =P44 -> 7543.8218 | Q102: =Q44 -> 7484.9351 | ... Y102: =Y44 -> 7013.8418
A103: "Low cost" | B103: kWh | C103: =SUM(J103:Y103) -> 75664.03 | D103: =NPV($C$4,J103:Y103) -> 35579.971 | J103: =J86 -> 0 | K103: =K86 -> 5456.4753 | L103: =L86 -> 5397.5887 | M103: =M86 -> 5338.702 | N103: =N86 -> 5279.8153 | O103: =O86 -> 5220.9287 | P103: =P86 -> 5162.042 | Q103: =Q86 -> 5103.1553 | ... Y103: =Y86 -> 4632.062
A104: Surplus Qualité | B104: kWh | C104: =SUM(J104:Y104) -> 35726.697 | D104: =NPV($C$4,J104:Y104) -> 16469.097 | J104: =J102-J103 -> 0 | K104: =K102-K103 -> 2381.7798 | L104: =L102-L103 -> 2381.7798 | M104: =M102-M103 -> 2381.7798 | N104: =N102-N103 -> 2381.7798 | O104: =O102-O103 -> 2381.7798 | P104: =P102-P103 -> 2381.7798 | Q104: =Q102-Q103 -> 2381.7798 | ... Y104: =Y102-Y103 -> 2381.7798
B105: % | C105: =C104/C102 -> 0.32073313 | D105: =D104/D102 -> 0.31641483
A107: LCOE | C107: EUR - € | E107: FCFA
A108: "Qualité" | B108: €/FCFA | C108: =C96/C102 -> 0.16205119 | D108: =D96/D102 -> 0.30107375 | E108: =C108*656 -> 106.30558 | F108: =D108*656 -> 197.50438
A109: "Low cost" | B109: €/FCFA | C109: =C97/C103 -> 0.37812282 | D109: =D97/D103 -> 0.48408858 | E109: =C109*656 -> 248.04857 | F109: =D109*656 -> 317.56211
A110: Différence Qualityé vs Low-cost | B110: €/FCFA | C110: =C109-C108 -> 0.21607163 | D110: =D109-D108 -> 0.18301484 | E110: =C110*656 -> 141.74299 | F110: =D110*656 -> 120.05773
B111: % | C111: =C110/C108 -> 1.3333542 | D111: =D110/D108 -> 0.60787378
A113: TRI | B113: =IRR(J98:Y98) -> 0.13919506
